ejni/__init__.py
ejni/utils.py
ejni-0.1.2.dist-info/METADATA
ejni-0.1.2.dist-info/WHEEL
ejni-0.1.2.dist-info/entry_points.txt
ejni-0.1.2.dist-info/licenses/LICENSE
ejni-0.1.2.dist-info/RECORD
