Metadata-Version: 2.4
Name: ejni
Version: 0.1.2
Summary: Add your description here
Author-email: kin9-0rz <kin9-0rz@outlook.com>
License-File: LICENSE
Requires-Python: >=3.8
Requires-Dist: apkutils>=2.0.0
